scovie/__init__.py
scovie/admin.py
scovie/apps.py
scovie/asgi.py
scovie/forms.py
scovie/management/__init__.py
scovie/management/commands/__init__.py
scovie/management/commands/firstinstall.py
scovie/management/commands/run_testserver.py
scovie/migrations/0001_initial.py
scovie/migrations/__init__.py
scovie/models.py
scovie/publish.py
scovie/settings/__init__.py
scovie/settings/base.py
scovie/settings/local.py
scovie/settings/prod.py
scovie/settings/test.py
scovie/static/admin/css/autocomplete.css
scovie/static/admin/css/base.css
scovie/static/admin/css/changelists.css
scovie/static/admin/css/dark_mode.css
scovie/static/admin/css/dashboard.css
scovie/static/admin/css/fonts.css
scovie/static/admin/css/forms.css
scovie/static/admin/css/login.css
scovie/static/admin/css/nav_sidebar.css
scovie/static/admin/css/responsive.css
scovie/static/admin/css/responsive_rtl.css
scovie/static/admin/css/rtl.css
scovie/static/admin/css/vendor/select2/LICENSE-SELECT2.md
scovie/static/admin/css/vendor/select2/select2.css
scovie/static/admin/css/vendor/select2/select2.min.css
scovie/static/admin/css/widgets.css
scovie/static/admin/fonts/LICENSE.txt
scovie/static/admin/fonts/README.txt
scovie/static/admin/fonts/Roboto-Bold-webfont.woff
scovie/static/admin/fonts/Roboto-Light-webfont.woff
scovie/static/admin/fonts/Roboto-Regular-webfont.woff
scovie/static/admin/img/LICENSE
scovie/static/admin/img/README.txt
scovie/static/admin/img/calendar-icons.svg
scovie/static/admin/img/gis/move_vertex_off.svg
scovie/static/admin/img/gis/move_vertex_on.svg
scovie/static/admin/img/icon-addlink.svg
scovie/static/admin/img/icon-alert.svg
scovie/static/admin/img/icon-calendar.svg
scovie/static/admin/img/icon-changelink.svg
scovie/static/admin/img/icon-clock.svg
scovie/static/admin/img/icon-deletelink.svg
scovie/static/admin/img/icon-no.svg
scovie/static/admin/img/icon-unknown-alt.svg
scovie/static/admin/img/icon-unknown.svg
scovie/static/admin/img/icon-viewlink.svg
scovie/static/admin/img/icon-yes.svg
scovie-0.0.5.dist-info/LICENSE
scovie-0.0.5.dist-info/METADATA
scovie-0.0.5.dist-info/WHEEL
scovie-0.0.5.dist-info/entry_points.txt
scovie-0.0.5.dist-info/RECORD
