Metadata-Version: 2.1
Name: scovie
Version: 0.0.5
Summary: Scovie is an open-source digital signage system for high schools.
Home-page: https://github.com/eldertek/scovie
License: GPL-3.0-or-later
Author: André Théo LAURET
Author-email: andrelauret@eclipse-technology.eu
Maintainer: André Théo LAURET
Maintainer-email: andrelauret@eclipse-technology.eu
Requires-Python: >=3.9,<4.0.0
Classifier: License :: OSI Approved :: GNU General Public License v3 or later (GPLv3+)
Classifier: Programming Language :: Python :: 3
Classifier: Programming Language :: Python :: 3.9
Classifier: Programming Language :: Python :: 3.10
Classifier: Programming Language :: Python :: 3.11
Requires-Dist: django-solo (>=2.1.0,<3.0.0)
Requires-Dist: pillow (>=9.5.0,<10.0.0)
Requires-Dist: pip (>=23.1.2,<24.0.0)
Project-URL: Bug Tracker, https://github.com/eldertek/scovie/issues
